CHANGELOG.rst
LICENSE.txt
MANIFEST.in
README.rst
setup.cfg
setup.py
swaggerpython/__init__.py
swaggerpython/client.py
swaggerpython/codegen.py
swaggerpython/http_client.py
swaggerpython/processors.py
swaggerpython/swagger_model.py
swaggerpython.egg-info/PKG-INFO
swaggerpython.egg-info/SOURCES.txt
swaggerpython.egg-info/dependency_links.txt
swaggerpython.egg-info/entry_points.txt
swaggerpython.egg-info/requires.txt
swaggerpython.egg-info/top_level.txt