Metadata-Version: 1.1
Name: swaggerpython
Version: 0.2.2
Summary: Library for accessing Swagger-enabled API's
Home-page: https://github.com/poogles/swagger-python
Author: Digium, Inc and Infectious Media
Author-email: sre@infectiousmedia.com
License: BSD 3-Clause License
Platform: UNKNOWN
Classifier: Development Status :: 1 - Planning
Classifier: Intended Audience :: Developers
Classifier: Topic :: Software Development :: Libraries :: Python Modules
Classifier: License :: OSI Approved :: BSD License
Classifier: Operating System :: OS Independent
Classifier: Programming Language :: Python
